mersal_alchemy/__init__.py
mersal_alchemy/orm.py
mersal_alchemy/py.typed
mersal_alchemy/sqlalchemy_outbox_storage.py
mersal_alchemy/sqlalchemy_saga_storage.py
mersal_alchemy/sqlalchemy_unit_of_work.py
mersal_alchemy-0.1.0.dist-info/METADATA
mersal_alchemy-0.1.0.dist-info/WHEEL
mersal_alchemy-0.1.0.dist-info/RECORD
